fine/__init__.py
fine/component.py
fine/conversion.py
fine/energySystemModel.py
fine/sourceSink.py
fine/storage.py
fine/transmission.py
fine/utils.py
fine/utilsETL.py
fine/IOManagement/__init__.py
fine/IOManagement/dictIO.py
fine/IOManagement/exploitOutput.py
fine/IOManagement/standardIO.py
fine/IOManagement/utilsIO.py
fine/IOManagement/xarrayIO.py
fine/aggregations/__init__.py
fine/aggregations/spatialAggregation/__init__.py
fine/aggregations/spatialAggregation/aggregation.py
fine/aggregations/spatialAggregation/grouping.py
fine/aggregations/spatialAggregation/groupingUtils.py
fine/aggregations/spatialAggregation/manager.py
fine/aggregations/spatialAggregation/managerUtils.py
fine/aggregations/technologyAggregation/__init__.py
fine/aggregations/technologyAggregation/techAggregation.py
fine/aggregations/technologyAggregation/techAggregationUtils.py
fine/expansionModules/__init__.py
fine/expansionModules/optimizeTSAmultiStage.py
fine/expansionModules/transformationPath.py
fine/subclasses/__init__.py
fine/subclasses/conversionDynamic.py
fine/subclasses/conversionPartLoad.py
fine/subclasses/endogenousTechnologicalLearning.py
fine/subclasses/lopf.py
fine-2.4.1.dist-info/LICENSE.txt
fine-2.4.1.dist-info/METADATA
fine-2.4.1.dist-info/WHEEL
fine-2.4.1.dist-info/top_level.txt
fine-2.4.1.dist-info/RECORD
