Metadata-Version: 2.2
Name: fine
Version: 2.4.1
Summary: Framework for integrated energy systems assessment
Author-email: Johannes Behrens <j.behrens@fz-juelich.de>, Theresa Klütz <t.kluetz@fz-juelich.de>
Maintainer-email: Johannes Behrens <j.behrens@fz-juelich.de>, Theresa Klütz <t.kluetz@fz-juelich.de>
Project-URL: homepage, https://www.fz-juelich.de/en/ice/ice-2/research-1/open_source/fine
Project-URL: repository, https://github.com/FZJ-IEK3-VSA/FINE
Project-URL: documentation, https://vsa-fine.readthedocs.io/en/master/
Keywords: energy assesment,energy system,optimization
Classifier: Intended Audience :: Science/Research
Classifier: License :: OSI Approved :: MIT License
Classifier: Natural Language :: English
Classifier: Operating System :: OS Independent
Classifier: Programming Language :: Python
Classifier: Programming Language :: Python :: 3
Classifier: Topic :: Scientific/Engineering :: Mathematics
Classifier: Topic :: Software Development :: Libraries :: Python Modules
Requires-Python: <3.13,>=3.10
License-File: LICENSE.txt
Requires-Dist: geopandas<=0.14.4
Requires-Dist: openpyxl<=3.1.5
Requires-Dist: matplotlib<=3.9.2
Requires-Dist: xlrd<=2.0.1
Requires-Dist: pyomo<=6.8.0
Requires-Dist: numpy<=1.26.4
Requires-Dist: pandas<=2.2.3,>=2
Requires-Dist: scipy<=1.14.1
Requires-Dist: scikit-learn<=1.5.2,>=1.2
Requires-Dist: xarray<=2024.3
Requires-Dist: rasterio<=1.4.1
Requires-Dist: netcdf4<=1.7.2
Requires-Dist: tsam
Requires-Dist: pwlf<=2.2.1
Requires-Dist: psutil<=5.9.8
Requires-Dist: gurobi-logtools<=3.1.0
Requires-Dist: ipykernel<=6.29.5
Provides-Extra: develop
Requires-Dist: sphinx<=7.4.4; extra == "develop"
Requires-Dist: sphinx_rtd_theme<=2.0.0; extra == "develop"
Requires-Dist: myst-parser<=2.0.0; extra == "develop"
Requires-Dist: pytest<=8.3.3; extra == "develop"
Requires-Dist: pytest-cov<=4.1.0; extra == "develop"
Requires-Dist: pytest-xdist<=3.6.1; extra == "develop"
Requires-Dist: nbval<=0.11.0; extra == "develop"
Requires-Dist: ruff<0.7.0; extra == "develop"
